Metadata-Version: 1.1
Name: EHRcorral
Version: 0.0.3
Summary: EHRcorral cross-matches and links electronic medical records for the purpose of de-duplication
Home-page: https://github.com/nsh87/ehrcorral
Author: Nikhil Haas
Author-email: nikhil@nikhilhaas.com
License: ISCL
Keywords: record linkage ehr patient matching
Platform: UNKNOWN
Classifier: Development Status :: 2 - Pre-Alpha
Classifier: Intended Audience :: Developers
Classifier: License :: OSI Approved :: ISC License (ISCL)
Classifier: Natural Language :: English
Classifier: Programming Language :: Python :: 2
Classifier: Programming Language :: Python :: 2.6
Classifier: Programming Language :: Python :: 2.7
Classifier: Programming Language :: Python :: 3
Classifier: Programming Language :: Python :: 3.3
Classifier: Programming Language :: Python :: 3.4
